benchmarking/__init__.py
benchmarking/output.py
benchmarking/standard.py
revarie/__init__.py
revarie/__version__.py
revarie/fvariogram.py
revarie/models.py
revarie/revarie.py
revarie/variogram.py
revarie/benchmarking/__init__.py
revarie/benchmarking/output.py
revarie/benchmarking/standard.py
revarie/test/__init__.py
revarie/test/test_fvariogram.py
revarie/test/test_revarie.py
revarie/test/test_variogram.py
test/__init__.py
test/test_fvariogram.py
test/test_revarie.py
test/test_variogram.py
revarie-1.4.0.dist-info/LICENSE
revarie-1.4.0.dist-info/METADATA
revarie-1.4.0.dist-info/WHEEL
revarie-1.4.0.dist-info/top_level.txt
revarie-1.4.0.dist-info/RECORD
