Metadata-Version: 2.1
Name: revarie
Version: 1.4.0
Summary: Variogram manipulation and field generation toolbox
Home-page: https://github.com/deanrp2/revarie
Author: Dean Price
Author-email: deanrp@umich.edu
License: MIT
Platform: UNKNOWN
Classifier: License :: OSI Approved :: MIT License
Classifier: Programming Language :: Python :: 3
Classifier: Programming Language :: Python :: 3.7
Requires-Dist: numpy-indexed
